cumulus/__init__.py
cumulus/api.py
cumulus/base.py
cumulus/models.py
cumulus/util.py
py_nvidia_cumulus-0.0.4.dist-info/LICENSE
py_nvidia_cumulus-0.0.4.dist-info/METADATA
py_nvidia_cumulus-0.0.4.dist-info/WHEEL
py_nvidia_cumulus-0.0.4.dist-info/RECORD
