Metadata-Version: 2.1
Name: py-nvidia-cumulus
Version: 0.0.4
Summary: Python API Client for Nvidia Cumulus
Home-page: https://github.com/NCCloud/py-nvidia-cumulus
License: Apache-2.0
Author: Namecheap Cloud
Author-email: cloud@namecheap.com
Requires-Python: >=3.8.1,<4.0.0
Classifier: License :: OSI Approved :: Apache Software License
Classifier: Operating System :: OS Independent
Classifier: Programming Language :: Python :: 3
Classifier: Programming Language :: Python :: 3.9
Classifier: Programming Language :: Python :: 3.10
Classifier: Programming Language :: Python :: 3.11
Classifier: Programming Language :: Python :: 3
Requires-Dist: requests (>=2.30.0,<3.0.0)
Project-URL: Repository, https://github.com/NCCloud/py-nvidia-cumulus
